ansicolors-1.1.7.dist-info/DESCRIPTION.rst
ansicolors-1.1.7.dist-info/METADATA
ansicolors-1.1.7.dist-info/RECORD
ansicolors-1.1.7.dist-info/WHEEL
ansicolors-1.1.7.dist-info/metadata.json
ansicolors-1.1.7.dist-info/top_level.txt
colors/__init__.py
colors/colors.py
colors/csscolors.py
colors/version.py
